setup.py
dist_uploadTest_exercise/Binomialdistribution.py
dist_uploadTest_exercise/Gaussiandistribution.py
dist_uploadTest_exercise/Generaldistribution.py
dist_uploadTest_exercise/__init__.py
dist_uploadTest_exercise.egg-info/PKG-INFO
dist_uploadTest_exercise.egg-info/SOURCES.txt
dist_uploadTest_exercise.egg-info/dependency_links.txt
dist_uploadTest_exercise.egg-info/not-zip-safe
dist_uploadTest_exercise.egg-info/top_level.txt