Metadata-Version: 1.0
Name: dist-uploadTest-exercise
Version: 0.1
Summary: Gaussian distributions, Binomial distributions
Home-page: UNKNOWN
Author: UNKNOWN
Author-email: UNKNOWN
License: UNKNOWN
Platform: UNKNOWN
